[{"code":"01AS0001","name":"Арбитражный суд Республики Адыгея","court_type":"AS","address":"385000, г Майкоп, ул Краснооктябрьская, д 15","oktmo":"79701000001","inn":"0105018622","website":"http://adyg.arbitr.ru","objectguid":null,"method":"locality","status":"found_by_locality"},{"code":"01MS0001","name":"Судебный участок № 1 г. Майкопа","court_type":"MS","address":"385009, г Майкоп, п Западный, ул Юбилейная, д 23А","oktmo":"79701000001","inn":null,"website":"http://maikop1.adg.msudrf.ru","objectguid":null,"method":"locality","status":"found_by_locality"},{"code":"01MS0002","name":"Судебный участок № 2 г. Майкопа","court_type":"MS","address":"385000, г Майкоп, ул Крестьянская, д 236","oktmo":"79701000001","inn":null,"website":"http://maikop2.adg.msudrf.ru","objectguid":null,"method":"locality","status":"found_by_locality"},{"code":"01MS0003","name":"Судебный участок № 3 г. Майкопа","court_type":"MS","address":"385000, г Майкоп, ул Курганная, д 227","oktmo":"79701000001","inn":null,"website":"http://maikop3.adg.msudrf.ru","objectguid":null,"method":"locality","status":"found_by_locality"},{"code":"01MS0004","name":"Судебный участок № 4 г. Майкопа","court_type":"MS","address":"385018, г Майкоп, ул Юннатов, д 2Е","oktmo":"79701000001","inn":null,"website":"http://maikop4.adg.msudrf.ru","objectguid":null,"method":"locality","status":"found_by_locality"},{"code":"01MS0005","name":"Судебный участок № 5 г. Майкопа","court_type":"MS","address":"385008, г Майкоп, ул 12 Марта, д 155","oktmo":"79701000001","inn":null,"website":"http://maikop5.adg.msudrf.ru","objectguid":null,"method":"locality","status":"found_by_locality"},{"code":"01MS0006","name":"Судебный участок № 6 г. Майкопа","court_type":"MS","address":"385008, г Майкоп, ул 12 Марта, д 155","oktmo":"79701000001","inn":null,"website":"http://maikop6.adg.msudrf.ru","objectguid":null,"method":"locality","status":"found_by_locality"},{"code":"01MS0007","name":"Судебный участок № 7 г. Майкопа","court_type":"MS","address":"385012, г Майкоп, ул Спортивная, д 39А","oktmo":"79701000001","inn":null,"website":"http://maikop7.adg.msudrf.ru","objectguid":null,"method":"locality","status":"found_by_locality"},{"code":"01MS0008","name":"Судебный участок № 8 г. Майкопа","court_type":"MS","address":"385012, г Майкоп, ул Кирпичная, д 75","oktmo":"79701000001","inn":null,"website":"http://maikop8.adg.msudrf.ru","objectguid":null,"method":"locality","status":"found_by_locality"},{"code":"01MS0009","name":"Судебный участок № 1 Майкопского района Республики Адыгея","court_type":"MS","address":"385730, Респ Адыгея, п Тульский, ул Садовая, д 51А","oktmo":"79622455101","inn":null,"website":"http://mkpr1.adg.msudrf.ru","objectguid":null,"method":"locality","status":"found_by_locality"},{"code":"01MS0010","name":"Судебный участок № 2 Майкопского района Республики Адыгея","court_type":"MS","address":"385750, Респ Адыгея, Майкопский р-н, п Каменномостский, ул Мира, д 48","oktmo":"79622457101","inn":null,"website":"http://mkpr2.adg.msudrf.ru","objectguid":null,"method":"locality","status":"found_by_locality"},{"code":"01MS0011","name":"Судебный участок № 3 Майкопского района Республики Адыгея","court_type":"MS","address":"385730, Респ Адыгея, п Тульский, ул Садовая, д 51А","oktmo":"79622455101","inn":null,"website":"http://mkpr3.adg.msudrf.ru","objectguid":null,"method":"locality","status":"found_by_locality"},{"code":"01MS0012","name":"Судебный участок № 1 Гиагинского района Республики Адыгея","court_type":"MS","address":"385600, Респ Адыгея, ст-ца Гиагинская, ул Красная, д 266","oktmo":"79605407101","inn":null,"website":"http://giagr1.adg.msudrf.ru","objectguid":null,"method":"locality","status":"found_by_locality"},{"code":"01MS0013","name":"Судебный участок № 2 Гиагинского района Республики Адыгея","court_type":"MS","address":"385635, Респ Адыгея, Гиагинский р-н, ст-ца Дондуковская, ул Ленина, влд 145","oktmo":"79605410101","inn":null,"website":"http://giagr2.adg.msudrf.ru","objectguid":null,"method":"locality","status":"found_by_locality"},{"code":"01MS0014","name":"Судебный участок № 1 Кошехабльского района Республики Адыгея","court_type":"MS","address":"385400, Респ Адыгея, аул Кошехабль, ул Ленина, д 12","oktmo":"79615420101","inn":null,"website":"http://koshr1.adg.msudrf.ru","objectguid":null,"method":"locality","status":"found_by_locality"},{"code":"01MS0015","name":"Судебный участок № 2 Кошехабльского района Республики Адыгея","court_type":"MS","address":"385436, Респ Адыгея, Кошехабльский р-н, с Вольное, ул Чапаева, д 44","oktmo":"79615408101","inn":null,"website":"http://koshr2.adg.msudrf.ru","objectguid":null,"method":"locality","status":"found_by_locality"},{"code":"01MS0016","name":"Судебный участок № 1 Красногвардейского района Республики Адыгея","court_type":"MS","address":"385300, Респ Адыгея, с Красногвардейское, ул Чапаева, влд 91","oktmo":"79618420101","inn":null,"website":"http://krasr1.adg.msudrf.ru","objectguid":null,"method":"locality","status":"found_by_locality"},{"code":"01MS0017","name":"Судебный участок № 2 Красногвардейского района Республики Адыгея","court_type":"MS","address":"385300, Респ Адыгея, с Красногвардейское, ул Чапаева, влд 91","oktmo":"79618420101","inn":null,"website":"http://krasr2.adg.msudrf.ru","objectguid":null,"method":"locality","status":"found_by_locality"},{"code":"01MS0018","name":"Судебный участок № 1 Тахтамукайского района Республики Адыгея","court_type":"MS","address":"385100, Респ Адыгея, аул Тахтамукай, ул Ш.Хакурате, д 53","oktmo":"79630420101","inn":null,"website":"http://tahr1.adg.msudrf.ru","objectguid":null,"method":"locality","status":"found_by_locality"},{"code":"01MS0019","name":"Судебный участок № 2 Тахтамукайского района Республики Адыгея","court_type":"MS","address":"385142, Респ Адыгея, Тахтамукайский р-н, пгт Яблоновский, ул Гагарина, д 144/1 к 7, помещ 1Б","oktmo":"79630159051","inn":null,"website":"http://tahr2.adg.msudrf.ru","objectguid":null,"method":"locality","status":"found_by_locality"},{"code":"01MS0020","name":"Судебный участок № 3 Тахтамукайского района Республики Адыгея","court_type":"MS","address":"385130, Респ Адыгея, Тахтамукайский р-н, пгт Энем, ул Октябрьская, д 5/1","oktmo":"79630157051","inn":null,"website":"http://tahr3.adg.msudrf.ru","objectguid":null,"method":"locality","status":"found_by_locality"},{"code":"01MS0021","name":"Судебный участок Шовгеновского района Республики Адыгея","court_type":"MS","address":"385440, Респ Адыгея, аул Хакуринохабль, ул Шовгенова, д 5","oktmo":"79640430101","inn":null,"website":"http://shovr.adg.msudrf.ru","objectguid":null,"method":"locality","status":"found_by_locality"},{"code":"01MS0022","name":"Судебный участок № 1 г. Адыгейска","court_type":"MS","address":"385200, Респ Адыгея, г Адыгейск, ул Ленина, д 17","oktmo":"79703000001","inn":null,"website":"http://adg1.adg.msudrf.ru","objectguid":null,"method":"locality","status":"found_by_locality"},{"code":"01MS0023","name":"Судебный участок № 2 Теучежского района Республики Адыгея","court_type":"MS","address":"385230, Респ Адыгея, аул Понежукай, ул Ленина, д 71","oktmo":"79633430101","inn":null,"website":"http://teur2.adg.msudrf.ru","objectguid":null,"method":"locality","status":"found_by_locality"},{"code":"01MS0024","name":"Судебный участок № 4 Тахтамукайского района Республики Адыгея","court_type":"MS","address":"385142, Респ Адыгея, Тахтамукайский р-н, пгт Яблоновский, ул Лаухина, д 11","oktmo":"79630159051","inn":null,"website":"http://tahr4.adg.msudrf.ru/","objectguid":null,"method":"locality","status":"found_by_locality"},{"code":"01OS0000","name":"Верховный Суд Республики Адыгея","court_type":"OS","address":"385000, г Майкоп, ул Жуковского, д 32","oktmo":"79701000001","inn":"0105020332","website":"http://vs.adg.sudrf.ru","objectguid":null,"method":"locality","status":"found_by_locality"},{"code":"01RS0001","name":"Гиагинский районный суд Республики Адыгея","court_type":"RS","address":"385600, Респ Адыгея, ст-ца Гиагинская, ул Советская, д 35","oktmo":"79605407101","inn":null,"website":"http://giaginsky.adg.sudrf.ru","objectguid":null,"method":"locality","status":"found_by_locality"},{"code":"01RS0002","name":"Кошехабльский районный суд Республики Адыгея","court_type":"RS","address":"385400, Респ Адыгея, аул Кошехабль, ул Ленина, д 5А","oktmo":"79615420101","inn":null,"website":"http://koshehablsky.adg.sudrf.ru","objectguid":null,"method":"locality","status":"found_by_locality"},{"code":"01RS0003","name":"Красногвардейский районный суд Республики Адыгея","court_type":"RS","address":"385300, Респ Адыгея, с Красногвардейское, ул 50 лет Октября, д 22","oktmo":"79618420101","inn":null,"website":"http://krasnogvardeysky.adg.sudrf.ru","objectguid":null,"method":"locality","status":"found_by_locality"},{"code":"01RS0004","name":"Майкопский городской суд Республики Адыгея","court_type":"RS","address":"385000, г Майкоп, ул Первомайская, д 199","oktmo":"79701000001","inn":null,"website":"http://maikopsky.adg.sudrf.ru","objectguid":null,"method":"locality","status":"found_by_locality"},{"code":"01RS0005","name":"Майкопский районный суд Республики Адыгея","court_type":"RS","address":"385730, Респ Адыгея, п Тульский, ул Ленина, д 47","oktmo":"79622455101","inn":null,"website":"http://maikopskyr.adg.sudrf.ru","objectguid":null,"method":"locality","status":"found_by_locality"},{"code":"01RS0006","name":"Тахтамукайский районный суд Республики Адыгея","court_type":"RS","address":"385100, Респ Адыгея, аул Тахтамукай, ул Х.М.Совмена, д 14","oktmo":"79630420101","inn":null,"website":"http://tahtamukaysky.adg.sudrf.ru","objectguid":null,"method":"locality","status":"found_by_locality"},{"code":"01RS0007","name":"Теучежский районный суд Республики Адыгея","court_type":"RS","address":"385239, Респ Адыгея, г Адыгейск, х Псекупс, ул Ленина, д 17","oktmo":"79703000001","inn":null,"website":"http://teuchezhsky.adg.sudrf.ru","objectguid":null,"method":"locality","status":"found_by_locality"},{"code":"01RS0008","name":"Шовгеновский районный суд Республики Адыгея","court_type":"RS","address":"385440, Респ Адыгея, аул Хакуринохабль, ул Краснооктябрьская, д 88","oktmo":"79640430101","inn":null,"website":"http://shovgenovsky.adg.sudrf.ru","objectguid":null,"method":"locality","status":"found_by_locality"}]