[{"code":"44AS0031","name":"Арбитражный суд Костромской области","court_type":"AS","address":"156000, г Кострома, ул Долматова, д 2","oktmo":"34701000001","inn":"4401011695","website":"http://kostroma.arbitr.ru","objectguid":"22f8b5d8-3634-4cfb-9e0d-e064b57f3c34","status":"found"},{"code":"44MS0001","name":"Судебный участок № 1 Свердловского судебного района города Костромы","court_type":"MS","address":"156026, г Кострома, ул Советская, д 120","oktmo":"34701000001","inn":null,"website":"http://1.kst.msudrf.ru","objectguid":"9167e060-b2f2-46c8-8b68-72a3ad617a08","status":"found"},{"code":"44MS0002","name":"Судебный участок № 2 Свердловского судебного района города Костромы","court_type":"MS","address":"156026, г Кострома, ул Советская, д 120","oktmo":"34701000001","inn":null,"website":"http://2.kst.msudrf.ru","objectguid":"9167e060-b2f2-46c8-8b68-72a3ad617a08","status":"found"},{"code":"44MS0003","name":"Судебный участок № 3 Свердловского судебного района города Костромы","court_type":"MS","address":"156026, г Кострома, ул Советская, д 120","oktmo":"34701000001","inn":null,"website":"http://3.kst.msudrf.ru","objectguid":"9167e060-b2f2-46c8-8b68-72a3ad617a08","status":"found"},{"code":"44MS0004","name":"Судебный участок № 4 Свердловского судебного района города Костромы","court_type":"MS","address":"156026, г Кострома, ул Привокзальная, д 16А","oktmo":"34701000001","inn":null,"website":"http://4.kst.msudrf.ru","objectguid":"0217ad88-f403-47ee-bf02-3b9996cf19ff","status":"found"},{"code":"44MS0005","name":"Судебный участок № 5 Свердловского судебного района города Костромы","court_type":"MS","address":"156026, г Кострома, ул Советская, д 120","oktmo":"34701000001","inn":null,"website":"http://5.kst.msudrf.ru","objectguid":"9167e060-b2f2-46c8-8b68-72a3ad617a08","status":"found"},{"code":"44MS0006","name":"Судебный участок № 6 Свердловского судебного района города Костромы","court_type":"MS","address":"156026, г Кострома, ул Советская, д 120","oktmo":"34701000001","inn":null,"website":"http://6.kst.msudrf.ru","objectguid":"9167e060-b2f2-46c8-8b68-72a3ad617a08","status":"found"},{"code":"44MS0007","name":"Судебный участок № 7 Свердловского судебного района города Костромы","court_type":"MS","address":"156026, г Кострома, ул Советская, д 120","oktmo":"34701000001","inn":null,"website":"http://7.kst.msudrf.ru","objectguid":"9167e060-b2f2-46c8-8b68-72a3ad617a08","status":"found"},{"code":"44MS0008","name":"Судебный участок № 8 Ленинского судебного района города Костромы","court_type":"MS","address":"156026, г Кострома, ул Советская, д 120","oktmo":"34701000001","inn":null,"website":"http://8.kst.msudrf.ru","objectguid":"9167e060-b2f2-46c8-8b68-72a3ad617a08","status":"found"},{"code":"44MS0009","name":"Судебный участок № 9 Ленинского судебного района города Костромы","court_type":"MS","address":"156026, г Кострома, ул Советская, д 120","oktmo":"34701000001","inn":null,"website":"http://9.kst.msudrf.ru","objectguid":"9167e060-b2f2-46c8-8b68-72a3ad617a08","status":"found"},{"code":"44MS0010","name":"Судебный участок № 10 Ленинского судебного района города Костромы","court_type":"MS","address":"156026, г Кострома, ул Советская, д 120","oktmo":"34701000001","inn":null,"website":"http://10.kst.msudrf.ru","objectguid":"9167e060-b2f2-46c8-8b68-72a3ad617a08","status":"found"},{"code":"44MS0011","name":"Судебный участок № 11 Ленинского судебного района города Костромы","court_type":"MS","address":"156026, г Кострома, ул Советская, д 120","oktmo":"34701000001","inn":null,"website":"http://11.kst.msudrf.ru","objectguid":"9167e060-b2f2-46c8-8b68-72a3ad617a08","status":"found"},{"code":"44MS0012","name":"Судебный участок № 12 Ленинского судебного района города Костромы","court_type":"MS","address":"156026, г Кострома, ул Советская, д 120","oktmo":"34701000001","inn":null,"website":"http://12.kst.msudrf.ru","objectguid":"9167e060-b2f2-46c8-8b68-72a3ad617a08","status":"found"},{"code":"44MS0013","name":"Судебный участок № 13 Димитровского судебного района города Костромы","court_type":"MS","address":"156010, г Кострома, ул Южная, д 8","oktmo":"34701000001","inn":null,"website":"http://13.kst.msudrf.ru","objectguid":"1d85148f-25fc-460b-8406-0a1626bc9a4c","status":"found"},{"code":"44MS0014","name":"Судебный участок № 14 Димитровского судебного района города Костромы","court_type":"MS","address":"156010, г Кострома, ул Южная, д 8","oktmo":"34701000001","inn":null,"website":"http://14.kst.msudrf.ru","objectguid":"1d85148f-25fc-460b-8406-0a1626bc9a4c","status":"found"},{"code":"44MS0015","name":"Судебный участок № 15 Димитровского судебного района города Костромы","court_type":"MS","address":"156010, г Кострома, ул Южная, д 8","oktmo":"34701000001","inn":null,"website":"http://15.kst.msudrf.ru","objectguid":"1d85148f-25fc-460b-8406-0a1626bc9a4c","status":"found"},{"code":"44MS0016","name":"Судебный участок № 16 Нерехтского судебного района города Волгореченска","court_type":"MS","address":"156901, Костромская обл, г Волгореченск, ул Имени 50-летия Ленинского Комсомола, д 58","oktmo":"34706000001","inn":null,"website":"http://16.kst.msudrf.ru","objectguid":"3a394c57-1130-460b-941f-f23bfe22e281","status":"found"},{"code":"44MS0017","name":"Судебный участок № 17 Костромского судебного района","court_type":"MS","address":"156026, г Кострома, ул Привокзальная, д 16А","oktmo":"34701000001","inn":null,"website":"http://17.kst.msudrf.ru","objectguid":"0217ad88-f403-47ee-bf02-3b9996cf19ff","status":"found"},{"code":"44MS0018","name":"Судебный участок № 18 Костромского судебного района","court_type":"MS","address":"156026, г Кострома, ул Привокзальная, д 16А","oktmo":"34701000001","inn":null,"website":"http://18.kst.msudrf.ru","objectguid":"0217ad88-f403-47ee-bf02-3b9996cf19ff","status":"found"},{"code":"44MS0019","name":"Судебный участок № 19 Нерехтского судебного района","court_type":"MS","address":"157800, Костромская обл, г Нерехта, ул Красноармейская, д 19","oktmo":"34626101001","inn":null,"website":"http://19.kst.msudrf.ru","objectguid":"44a9e26b-57fd-4c04-ba37-c76058024db1","status":"found"},{"code":"44MS0020","name":"Судебный участок № 20 Нерехтского судебного района","court_type":"MS","address":"157800, Костромская обл, г Нерехта, ул Красноармейская, д 19","oktmo":"34626101001","inn":null,"website":"http://20.kst.msudrf.ru","objectguid":"44a9e26b-57fd-4c04-ba37-c76058024db1","status":"found"},{"code":"44MS0021","name":"Судебный участок № 21 Буйского судебного района","court_type":"MS","address":"157006, Костромская обл, г Буй, ул 10 годовщины Октября, д 5","oktmo":"34705000001","inn":null,"website":"http://21.kst.msudrf.ru","objectguid":"58545b7a-9107-4aec-bf08-d35a9e8609a9","status":"found"},{"code":"44MS0022","name":"Судебный участок № 22 Буйского судебного района","court_type":"MS","address":"157006, Костромская обл, г Буй, ул 10 годовщины Октября, д 5","oktmo":"34705000001","inn":null,"website":"http://22.kst.msudrf.ru","objectguid":"58545b7a-9107-4aec-bf08-d35a9e8609a9","status":"found"},{"code":"44MS0023","name":"Судебный участок № 23 Шарьинского судебного района","court_type":"MS","address":"157510, Костромская обл, г Шарья, пгт Ветлужский, ул Центральная, д 4","oktmo":"34730000056","inn":null,"website":"http://23.kst.msudrf.ru","objectguid":"ee6e6ddf-2454-4a4b-99c9-3667c83b9624","status":"found"},{"code":"44MS0024","name":"Судебный участок № 24 Шарьинского судебного района","court_type":"MS","address":"157510, Костромская обл, г Шарья, пгт Ветлужский, ул Центральная, д 4","oktmo":"34730000056","inn":null,"website":"http://24.kst.msudrf.ru","objectguid":"ee6e6ddf-2454-4a4b-99c9-3667c83b9624","status":"found"},{"code":"44MS0025","name":"Судебный участок № 25 Шарьинского судебного района","court_type":"MS","address":"157510, Костромская обл, г Шарья, пгт Ветлужский, ул Центральная, д 4","oktmo":"34730000056","inn":null,"website":"http://25.kst.msudrf.ru","objectguid":"ee6e6ddf-2454-4a4b-99c9-3667c83b9624","status":"found"},{"code":"44MS0026","name":"Судебный участок № 26 Мантуровского судебного района","court_type":"MS","address":"157300, Костромская обл, г Мантурово, ул Центральная, д 5А","oktmo":"34520000001","inn":null,"website":"http://26.kst.msudrf.ru","objectguid":"2188e00d-1597-496a-99ae-6b9450144433","status":"found"},{"code":"44MS0027","name":"Судебный участок № 27 Мантуровского судебного района","court_type":"MS","address":"157300, Костромская обл, г Мантурово, ул Центральная, д 5А","oktmo":"34520000001","inn":null,"website":"http://27.kst.msudrf.ru","objectguid":"2188e00d-1597-496a-99ae-6b9450144433","status":"found"},{"code":"44MS0028","name":"Судебный участок № 28 Галичского судебного района","court_type":"MS","address":"157202, Костромская обл, г Галич, ул Гладышева, д 122Б","oktmo":"34708000001","inn":null,"website":"http://28.kst.msudrf.ru","objectguid":"02a881a2-c27e-401f-becc-fbf7e0a67476","status":"found"},{"code":"44MS0029","name":"Судебный участок № 29 Галичского судебного района","court_type":"MS","address":"157202, Костромская обл, г Галич, ул Гладышева, д 122Б","oktmo":"34708000001","inn":null,"website":"http://29.kst.msudrf.ru","objectguid":"02a881a2-c27e-401f-becc-fbf7e0a67476","status":"found"},{"code":"44MS0030","name":"Судебный участок № 30 Красносельского судебного района","court_type":"MS","address":"157940, Костромская обл, пгт Красное-на-Волге, пл Красная, д 11","oktmo":"34516000051","inn":null,"website":"http://30.kst.msudrf.ru","objectguid":"c78b5630-cf8a-4906-a240-efef541b1554","status":"found"},{"code":"44MS0031","name":"Судебный участок № 31 Островского судебного района","court_type":"MS","address":"157860, Костромская обл, пгт Судиславль, ул Невского, д 5","oktmo":"34542000051","inn":null,"website":"http://31.kst.msudrf.ru","objectguid":"c1034598-44dc-4f49-b23e-c4d5fb759ced","status":"found"},{"code":"44MS0032","name":"Судебный участок № 32 Свердловского судебного района города Костромы","court_type":"MS","address":"156026, г Кострома, ул Советская, д 120","oktmo":"34701000001","inn":null,"website":"http://32.kst.msudrf.ru","objectguid":"9167e060-b2f2-46c8-8b68-72a3ad617a08","status":"found"},{"code":"44MS0033","name":"Судебный участок № 33 Нейского судебного района","court_type":"MS","address":"157330, Костромская обл, г Нея, ул Советская, д 42","oktmo":"34524000001","inn":null,"website":"http://33.kst.msudrf.ru","objectguid":"cdbf0719-758d-4cd4-a3de-bdbab4223320","status":"found"},{"code":"44MS0034","name":"Судебный участок № 34 Вохомского судебного района","court_type":"MS","address":"157760, Костромская обл, п Вохма, ул Советская, д 51","oktmo":"34506000101","inn":null,"website":"http://34.kst.msudrf.ru","objectguid":"88c04d38-6075-4a65-a2b2-3501b458497b","status":"found"},{"code":"44MS0035","name":"Судебный участок № 35 Чухломского судебного района","court_type":"MS","address":"157170, Костромская обл, г Солигалич, ул Вылузгина, д 4","oktmo":"34540000001","inn":null,"website":"http://35.kst.msudrf.ru","objectguid":"80195014-ebf3-415e-af89-8022cd347ed2","status":"found"},{"code":"44MS0036","name":"Судебный участок № 36 Свердловского судебного района города Костромы","court_type":"MS","address":"156026, г Кострома, ул Привокзальная, д 16А","oktmo":"34701000001","inn":null,"website":"http://36.kst.msudrf.ru","objectguid":"0217ad88-f403-47ee-bf02-3b9996cf19ff","status":"found"},{"code":"44MS0037","name":"Судебный участок № 37 Галичского судебного района","court_type":"MS","address":"157260, Костромская обл, п Антропово, ул Октябрьская, д 23","oktmo":"34502000101","inn":null,"website":"http://37.kst.msudrf.ru","objectguid":"66384545-fb43-4c0f-a7c1-4f0f80347671","status":"found"},{"code":"44MS0038","name":"Судебный участок № 38 Макарьевского судебного района","court_type":"MS","address":"157980, Костромская обл, пгт Кадый, ул Больничная, д 6","oktmo":"34510000051","inn":null,"website":"http://38.kst.msudrf.ru","objectguid":"e2df7361-3857-4a9d-be39-09b69dfde90b","status":"found"},{"code":"44MS0039","name":"Судебный участок № 39 Кологривского судебного района","court_type":"MS","address":"157440, Костромская обл, г Кологрив, ул Центральная, д 1","oktmo":"34512000001","inn":null,"website":"http://39.kst.msudrf.ru","objectguid":"c61ad3f6-ef11-45b8-9df7-69f57cb8ec0b","status":"found"},{"code":"44MS0040","name":"Судебный участок № 40 Макарьевского судебного района","court_type":"MS","address":"157460, Костромская обл, г Макарьев, пл Революции, д 34","oktmo":"34518000001","inn":null,"website":"http://40.kst.msudrf.ru","objectguid":"8f97b1b3-4022-4025-9843-7d7b17af119f","status":"found"},{"code":"44MS0041","name":"Судебный участок № 41 Кологривского судебного района","court_type":"MS","address":"157420, Костромская обл, с Георгиевское, ул Октябрьская, д 70","oktmo":"34522000101","inn":null,"website":"http://41.kst.msudrf.ru","objectguid":"369f3505-6c53-4015-a6da-457509cccd45","status":"found"},{"code":"44MS0042","name":"Судебный участок № 42 Вохомского судебного района","court_type":"MS","address":"157780, Костромская обл, с Боговарово, ул Победы, стр 47","oktmo":"34528000101","inn":null,"website":"http://42.kst.msudrf.ru","objectguid":"4dd6a488-6568-44ba-9984-73fe7ef9a820","status":"found"},{"code":"44MS0043","name":"Судебный участок № 43 Островского судебного района","court_type":"MS","address":"157900, Костромская обл, п Островское, ул Советская, д 99","oktmo":"34530000101","inn":null,"website":"http://43.kst.msudrf.ru","objectguid":"6d193775-c319-4b00-8a19-2ca1beb4036d","status":"found"},{"code":"44MS0044","name":"Судебный участок № 44 Павинского судебного района","court_type":"MS","address":"157650, Костромская обл, с Павино, ул Елькина, д 3","oktmo":"34532000101","inn":null,"website":"http://44.kst.msudrf.ru","objectguid":"740fa7f8-a16c-411b-a435-9abdfd68ec78","status":"found"},{"code":"44MS0045","name":"Судебный участок № 45 Нейского судебного района","court_type":"MS","address":"157270, Костромская обл, с Парфеньево, ул Ленина, д 58","oktmo":"34534000101","inn":null,"website":"http://45.kst.msudrf.ru","objectguid":"1eb55fd6-90c2-4852-af7e-bbfead66dd9c","status":"found"},{"code":"44MS0046","name":"Судебный участок № 46 Шарьинского судебного района","court_type":"MS","address":"157580, Костромская обл, пгт Поназырево, ул Вокзальная, д 29","oktmo":"34536000051","inn":null,"website":"http://46.kst.msudrf.ru","objectguid":"a3f3bda5-bee6-4de2-b615-dc7da0a6f8fc","status":"found"},{"code":"44MS0047","name":"Судебный участок № 47 Павинского судебного района","court_type":"MS","address":"157630, Костромская обл, с Пыщуг, ул Чкалова, д 7","oktmo":"34538000101","inn":null,"website":"http://47.kst.msudrf.ru","objectguid":"47d9d7c6-6418-472e-8cc3-6b7d1138b76c","status":"found"},{"code":"44MS0048","name":"Судебный участок № 48 Буйского судебного района","court_type":"MS","address":"157080, Костромская обл, пгт Сусанино, ул Октябрьская, д 2","oktmo":"34544000051","inn":null,"website":"http://48.kst.msudrf.ru","objectguid":"02e94e3b-3ec5-41f0-983b-95f5c2a67bee","status":"found"},{"code":"44MS0049","name":"Судебный участок № 49 Чухломского судебного района","court_type":"MS","address":"157130, Костромская обл, г Чухлома, ул Калинина, д 1","oktmo":"34546000001","inn":null,"website":"http://49.kst.msudrf.ru","objectguid":"a0ea3b48-73c4-4cb7-9a55-501826627bf6","status":"found"},{"code":"44OS0000","name":"Костромской областной суд","court_type":"OS","address":"156029, г Кострома, ул Скворцова, д 3","oktmo":"34701000001","inn":"4401004730","website":"http://oblsud.kst.sudrf.ru","objectguid":"08541dfa-afd3-4da4-a37f-e2205b6ee1d1","status":"found"},{"code":"44RS0001","name":"Свердловский районный суд г. Костромы","court_type":"RS","address":"156000, г Кострома, ул Долматова, д 14","oktmo":"34701000001","inn":null,"website":"http://sverdlovsky.kst.sudrf.ru","objectguid":"5a0c6497-2721-4555-a7c1-41579413d928","status":"found"},{"code":"44RS0002","name":"Ленинский районный суд г. Костромы","court_type":"RS","address":"156013, г Кострома, пр-кт Мира, д 51","oktmo":"34701000001","inn":null,"website":"http://leninsky.kst.sudrf.ru","objectguid":"c6fc8825-34fe-490f-bb6d-26a803f39317","status":"found"},{"code":"44RS0003","name":"Шарьинский районный суд Костромской области","court_type":"RS","address":"157500, Костромская обл, г Шарья, ул Ольги Степановой, д 66","oktmo":"34730000001","inn":null,"website":"http://sharinsky.kst.sudrf.ru","objectguid":"14be38f6-6239-44eb-a254-deb5d7e196ae","status":"found"},{"code":"44RS0004","name":"Мантуровский районный суд Костромской области","court_type":"RS","address":"157300, Костромская обл, г Мантурово, ул Советская, д 27А","oktmo":"34520000001","inn":null,"website":"http://manturovsky.kst.sudrf.ru","objectguid":"0970ad9b-af5c-4041-82eb-df392669582d","status":"found"},{"code":"44RS0005","name":"Буйский районный суд Костромской области","court_type":"RS","address":"157000, Костромская обл, г Буй, пл Революции, д 13","oktmo":"34705000001","inn":null,"website":"http://buisky.kst.sudrf.ru","objectguid":"b52317c4-41ed-46be-a25f-91aff0a37bb8","status":"found"},{"code":"44RS0006","name":"Галичский районный суд Костромской области","court_type":"RS","address":"157201, Костромская обл, г Галич, пл Революции, д 27А","oktmo":"34708000001","inn":null,"website":"http://galichsky.kst.sudrf.ru","objectguid":"2aed5b10-4055-4260-8202-790997107e14","status":"found"},{"code":"44RS0009","name":"Павинский районный суд Костромской области","court_type":"RS","address":"157650, Костромская обл, с Павино, ул Механизаторов, стр 11","oktmo":"34532000101","inn":null,"website":"http://pavinsky.kst.sudrf.ru","objectguid":"d3fb035e-7415-4f72-8e2b-16b0aa7da15e","status":"found"},{"code":"44RS0011","name":"Нейский районный суд Костромской области","court_type":"RS","address":"157330, Костромская обл, г Нея, ул Советская, д 22","oktmo":"34524000001","inn":null,"website":"http://neisky.kst.sudrf.ru","objectguid":"d2d627f3-28bc-4a40-982f-543428dd9d4b","status":"found"},{"code":"44RS0013","name":"Красносельский районный суд Костромской области","court_type":"RS","address":"157940, Костромская обл, пгт Красное-на-Волге, ул Луначарского, д 12","oktmo":"34516000051","inn":null,"website":"http://krasnoselsky.kst.sudrf.ru","objectguid":"d913fc6f-b5b7-4e16-b114-f671f9f501a1","status":"found"},{"code":"44RS0014","name":"Островский районный суд Костромской области","court_type":"RS","address":"157900, Костромская обл, п Островское, ул Советская, д 41","oktmo":"34530000101","inn":null,"website":"http://ostrovsky.kst.sudrf.ru","objectguid":"a9229112-4a85-4a8d-8817-f07ca4c44df3","status":"found"},{"code":"44RS0015","name":"Вохомский районный суд Костромской области","court_type":"RS","address":"157760, Костромская обл, п Вохма, ул Советская, д 39А","oktmo":"34506000101","inn":null,"website":"http://vohomsky.kst.sudrf.ru","objectguid":"388e3c20-213b-4e74-9d4f-0a65fe822bc0","status":"found"},{"code":"44RS0019","name":"Чухломский районный суд Костромской области","court_type":"RS","address":"157130, Костромская обл, г Чухлома, ул Ленина, д 1А","oktmo":"34546000001","inn":null,"website":"http://chuhlomsky.kst.sudrf.ru","objectguid":"9e8a34bc-de5f-44d5-a1cb-06da272e1b3e","status":"found"},{"code":"44RS0023","name":"Макарьевский районный суд Костромской области","court_type":"RS","address":"157460, Костромская обл, г Макарьев, пл Революции, д 3","oktmo":"34518000001","inn":null,"website":"http://makarievsky.kst.sudrf.ru","objectguid":"3421a53b-7777-429e-8e39-342cd3c1419d","status":"found"},{"code":"44RS0024","name":"Кологривский районный суд Костромской области","court_type":"RS","address":"157440, Костромская обл, г Кологрив, ул Кирова, д 28","oktmo":"34512000001","inn":null,"website":"http://kologrivsky.kst.sudrf.ru","objectguid":"35c8a6b6-03a2-4962-941f-84b0f539d3a3","status":"found"},{"code":"44RS0026","name":"Димитровский районный суд г. Костромы","court_type":"RS","address":"156001, г Кострома, пер Инженерный, д 1А","oktmo":"34701000001","inn":null,"website":"http://dimitrovsky.kst.sudrf.ru","objectguid":"7da00524-63ed-491b-afd6-5d2d63c90230","status":"found"},{"code":"44RS0027","name":"Нерехтский районный суд Костромской области","court_type":"RS","address":"157800, Костромская обл, г Нерехта, ул Красноармейская, д 6","oktmo":"34626101001","inn":null,"website":"http://nerehtsky.kst.sudrf.ru","objectguid":"36b75328-b0eb-472a-afcf-f653caa97112","status":"found"},{"code":"44RS0028","name":"Костромской районный суд Костромской области","court_type":"RS","address":"156000, г Кострома, ул Шагова, д 1","oktmo":"34701000001","inn":null,"website":"http://kostromskoy.kst.sudrf.ru","objectguid":"315051f6-fdfc-4f31-8507-8aed4cb52da3","status":"found"}]