[{"code":"09AS0025","name":"Арбитражный суд Карачаево-Черкесской Республики","court_type":"AS","address":"369001, г Черкесск, ул Ленина, д 9","oktmo":"91603460101","inn":"0901026251","website":"http://askchr.arbitr.ru","objectguid":"4f6991af-0859-4a67-8bc0-749cf942711e","status":"found"},{"code":"09MS0001","name":"Судебный участок № 1 судебного района г. Черкесска","court_type":"MS","address":"369000, г Черкесск, ул Им Ворошилова, д 16","oktmo":"91701000001","inn":null,"website":"http://cherkessk1.kchr.msudrf.ru","objectguid":"640bff19-064d-4fdc-937b-0ea1ec5e3695","status":"found"},{"code":"09MS0002","name":"Судебный участок № 2 судебного района г. Черкесска","court_type":"MS","address":"369000, г Черкесск, ул Им Ворошилова, д 16","oktmo":"91701000001","inn":null,"website":"http://cherkessk2.kchr.msudrf.ru","objectguid":"640bff19-064d-4fdc-937b-0ea1ec5e3695","status":"found"},{"code":"09MS0003","name":"Судебный участок № 3 судебного района г. Черкесска","court_type":"MS","address":"369000, г Черкесск, ул Им Ворошилова, д 16","oktmo":"91701000001","inn":null,"website":"http://cherkessk3.kchr.msudrf.ru","objectguid":"640bff19-064d-4fdc-937b-0ea1ec5e3695","status":"found"},{"code":"09MS0004","name":"Судебный участок № 4 судебного района г. Черкесска","court_type":"MS","address":"369000, г Черкесск, ул Им Ворошилова, д 16","oktmo":"91701000001","inn":null,"website":"http://cherkessk4.kchr.msudrf.ru","objectguid":"640bff19-064d-4fdc-937b-0ea1ec5e3695","status":"found"},{"code":"09MS0005","name":"Судебный участок № 5 судебного района г. Черкесска","court_type":"MS","address":"369000, г Черкесск, ул Им Ворошилова, д 16","oktmo":"91701000001","inn":null,"website":"http://cherkessk5.kchr.msudrf.ru","objectguid":"640bff19-064d-4fdc-937b-0ea1ec5e3695","status":"found"},{"code":"09MS0006","name":"Судебный участок № 6 судебного района г. Черкесска","court_type":"MS","address":"369000, г Черкесск, ул Им Ворошилова, д 16","oktmo":"91701000001","inn":null,"website":"http://cherkessk6.kchr.msudrf.ru","objectguid":"640bff19-064d-4fdc-937b-0ea1ec5e3695","status":"found"},{"code":"09MS0007","name":"Судебный участок № 7 судебного района г. Черкесска","court_type":"MS","address":"369000, г Черкесск, ул Им Ворошилова, д 16","oktmo":"91701000001","inn":null,"website":"http://cherkessk7.kchr.msudrf.ru","objectguid":"640bff19-064d-4fdc-937b-0ea1ec5e3695","status":"found"},{"code":"09MS0008","name":"Судебный участок № 8 судебного района г. Черкесска","court_type":"MS","address":"369000, г Черкесск, ул Им Ворошилова, д 16","oktmo":"91701000001","inn":null,"website":"http://cherkessk8.kchr.msudrf.ru","objectguid":"640bff19-064d-4fdc-937b-0ea1ec5e3695","status":"found"},{"code":"09MS0009","name":"Судебный участок № 1 судебного района г. Карачаевска","court_type":"MS","address":"369204, Респ Карачаево-Черкесская, г Карачаевск, ул Ленина, д 39","oktmo":"91705000001","inn":null,"website":"http://karachaevsk1.kchr.msudrf.ru","objectguid":"4318d741-e24d-40e9-b751-8495721f9896","status":"found"},{"code":"09MS0010","name":"Судебный участок № 2 судебного района г. Карачаевска","court_type":"MS","address":"369204, Респ Карачаево-Черкесская, г Карачаевск, ул Ленина, д 39","oktmo":"91705000001","inn":null,"website":"http://karachaevsk2.kchr.msudrf.ru","objectguid":"4318d741-e24d-40e9-b751-8495721f9896","status":"found"},{"code":"09MS0011","name":"Судебный участок № 1 Карачаевского судебного района","court_type":"MS","address":"369204, Респ Карачаево-Черкесская, г Карачаевск, ул Ленина, д 39","oktmo":"91705000001","inn":null,"website":"http://krchrn1.kchr.msudrf.ru","objectguid":"4318d741-e24d-40e9-b751-8495721f9896","status":"found"},{"code":"09MS0012","name":"Судебный участок № 1 Зеленчукского судебного района","court_type":"MS","address":"369140, Респ Карачаево-Черкесская, ст-ца Зеленчукская, ул Ленина, д 100","oktmo":"91603460101","inn":null,"website":"http://zelenrn1.kchr.msudrf.ru","objectguid":"4c05694c-b5e6-4d81-859e-93b2bba6e6f0","status":"found"},{"code":"09MS0013","name":"Судебный участок № 2 Зеленчукского судебного района","court_type":"MS","address":"369140, Респ Карачаево-Черкесская, ст-ца Зеленчукская, ул Ленина, д 100","oktmo":"91603460101","inn":null,"website":"http://zelenrn2.kchr.msudrf.ru","objectguid":"4c05694c-b5e6-4d81-859e-93b2bba6e6f0","status":"found"},{"code":"09MS0014","name":"Судебный участок № 3 Зеленчукского судебного района","court_type":"MS","address":"369140, Респ Карачаево-Черкесская, ст-ца Зеленчукская, ул Ленина, д 100","oktmo":"91603460101","inn":null,"website":"http://zelenrn3.kchr.msudrf.ru","objectguid":"4c05694c-b5e6-4d81-859e-93b2bba6e6f0","status":"found"},{"code":"09MS0015","name":"Судебный участок № 1 Малокарачаевского судебного района","court_type":"MS","address":"369380, Респ Карачаево-Черкесская, с Учкекен, ул Ленина, зд 146","oktmo":"91620460101","inn":null,"website":"http://malokarrn1.kchr.msudrf.ru","objectguid":"df5e1054-b6fa-4b0d-82e9-f82c4592c2bc","status":"found"},{"code":"09MS0016","name":"Судебный участок № 2 Малокарачаевского судебного района","court_type":"MS","address":"369380, Респ Карачаево-Черкесская, с Учкекен, ул Ленина, зд 146","oktmo":"91620460101","inn":null,"website":"http://malokarrn2.kchr.msudrf.ru","objectguid":"df5e1054-b6fa-4b0d-82e9-f82c4592c2bc","status":"found"},{"code":"09MS0017","name":"Судебный участок № 1 Усть-Джегутинского судебного района","court_type":"MS","address":"369300, Респ Карачаево-Черкесская, г Усть-Джегута, ул Калинина, д 95","oktmo":"91635101001","inn":null,"website":"http://ust-djegrn1.kchr.msudrf.ru","objectguid":"17e4c517-1bd1-4c0a-8dad-ed45d49b3b11","status":"found"},{"code":"09MS0018","name":"Судебный участок № 2 Усть-Джегутинского судебного района","court_type":"MS","address":"369300, Респ Карачаево-Черкесская, г Усть-Джегута, ул Калинина, д 95","oktmo":"91635101001","inn":null,"website":"http://ust-djegrn2.kchr.msudrf.ru","objectguid":"17e4c517-1bd1-4c0a-8dad-ed45d49b3b11","status":"found"},{"code":"09MS0019","name":"Судебный участок № 3 Усть-Джегутинского судебного района","court_type":"MS","address":"369300, Респ Карачаево-Черкесская, г Усть-Джегута, ул Калинина, д 95","oktmo":"91635101001","inn":null,"website":"http://ust-djegrn3.kchr.msudrf.ru","objectguid":"17e4c517-1bd1-4c0a-8dad-ed45d49b3b11","status":"found"},{"code":"09MS0020","name":"Судебный участок № 1 Хабезского судебного района","court_type":"MS","address":"369400, Респ Карачаево-Черкесская, аул Хабез, ул У.Хабекова, д 85","oktmo":"91640440101","inn":null,"website":"http://habezrn1.kchr.msudrf.ru","objectguid":"a306ca98-f5d3-4fb8-93b8-b1a65cef4197","status":"found"},{"code":"09MS0021","name":"Судебный участок № 2 Хабезского судебного района","court_type":"MS","address":"369400, Респ Карачаево-Черкесская, аул Хабез, ул У.Хабекова, д 85","oktmo":"91640440101","inn":null,"website":"http://habezrn2.kchr.msudrf.ru","objectguid":"a306ca98-f5d3-4fb8-93b8-b1a65cef4197","status":"found"},{"code":"09MS0022","name":"Судебный участок № 1 Прикубанского судебного района","court_type":"MS","address":"369100, Респ Карачаево-Черкесская, Прикубанский р-н, п Кавказский, ул Гагарина, д 2А","oktmo":"91625420101","inn":null,"website":"http://prikubrn1.kchr.msudrf.ru","objectguid":"3c0ff8bf-4779-4b48-9f9b-0f3fa932ed1b","status":"found"},{"code":"09MS0023","name":"Судебный участок № 2 Прикубанского судебного района","court_type":"MS","address":"369100, Респ Карачаево-Черкесская, Прикубанский р-н, п Кавказский, ул Гагарина, д 2А","oktmo":"91625420101","inn":null,"website":"http://prikubrn2.kchr.msudrf.ru","objectguid":"3c0ff8bf-4779-4b48-9f9b-0f3fa932ed1b","status":"found"},{"code":"09MS0024","name":"Судебный участок № 1 Адыге-Хабльского судебного района","court_type":"MS","address":"369330, Респ Карачаево-Черкесская, аул Адыге-Хабль, ул Советская, д 15","oktmo":"91610405111","inn":null,"website":"http://adg-hablrn1.kchr.msudrf.ru","objectguid":"b4b571b3-434e-4c2c-8612-3d594a380173","status":"found"},{"code":"09MS0025","name":"Судебный участок № 1 Урупского судебного района","court_type":"MS","address":"369260, Респ Карачаево-Черкесская, ст-ца Преградная, ул Красная, д 110","oktmo":"91630425101","inn":null,"website":"http://uruprn1.kchr.msudrf.ru","objectguid":"87fbd57f-f930-4580-a2d9-e2bada1d3cab","status":"found"},{"code":"09MS0026","name":"Судебный участок № 9 судебного района г. Черкесска","court_type":"MS","address":"369000, г Черкесск, ул Им Ворошилова, д 16","oktmo":"91701000001","inn":null,"website":"http://cherkessk9.kchr.msudrf.ru/","objectguid":"640bff19-064d-4fdc-937b-0ea1ec5e3695","status":"found"},{"code":"09OS0000","name":"Верховный Суд Карачаево-Черкесской Республики","court_type":"OS","address":"369000, г Черкесск, ул М.Гаджаева, зд 4","oktmo":"91701000001","inn":"0901022218","website":"http://vs.kchr.sudrf.ru","objectguid":"a21a06fd-7f71-4250-bd79-57b4f187918f","status":"found"},{"code":"09RS0001","name":"Черкесский городской суд Карачаево-Черкесской Республики","court_type":"RS","address":"369000, г Черкесск, ул Им Ворошилова, д 24","oktmo":"91701000001","inn":null,"website":"http://cherkessky.kchr.sudrf.ru","objectguid":"2a0de29a-f64f-4e17-9dc6-2e2f116b89bf","status":"found"},{"code":"09RS0002","name":"Усть-Джегутинский районный суд Карачаево-Черкесской Республики","court_type":"RS","address":"369300, Респ Карачаево-Черкесская, г Усть-Джегута, ул Богатырева, д 38","oktmo":"91635101001","inn":null,"website":"http://ust-djegutinsky.kchr.sudrf.ru","objectguid":"9d21ace7-7b25-4d44-bcb0-04b521e61753","status":"found"},{"code":"09RS0003","name":"Карачаевский городской суд Карачаево-Черкесской Республики","court_type":"RS","address":"369200, Респ Карачаево-Черкесская, г Карачаевск, ул Байрамукова, д 1","oktmo":"91705000001","inn":null,"website":"http://karachaevskygor.kchr.sudrf.ru","objectguid":"bb428f2f-f763-449d-8dec-bb3ff036a8f3","status":"found"},{"code":"09RS0004","name":"Карачаевский районный суд Карачаево-Черкесской Республики","court_type":"RS","address":"369200, Респ Карачаево-Черкесская, г Карачаевск, ул Мира, д 9А","oktmo":"91705000001","inn":null,"website":"http://karachaevskyrai.kchr.sudrf.ru","objectguid":"4347ea79-ae14-4bb4-9d91-03d531e291b7","status":"found"},{"code":"09RS0005","name":"Малокарачаевский районный суд Карачаево-Черкесской Республики","court_type":"RS","address":"369380, Респ Карачаево-Черкесская, с Учкекен, ул Ленина, зд 116","oktmo":"91620460101","inn":null,"website":"http://malokarachaevsky.kchr.sudrf.ru","objectguid":"ae96b718-bf8d-4930-8c7b-28688e35bacd","status":"found"},{"code":"09RS0006","name":"Урупский районный суд Карачаево-Черкесской Республики","court_type":"RS","address":"369260, Респ Карачаево-Черкесская, ст-ца Преградная, ул Голоколосовой, д 47","oktmo":null,"inn":null,"website":"http://urupsky.kchr.sudrf.ru","objectguid":null,"status":"not_found"},{"code":"09RS0007","name":"Зеленчукский районный суд Карачаево-Черкесской Республики","court_type":"RS","address":"369140, Респ Карачаево-Черкесская, ст-ца Зеленчукская, ул Мира, д 21А","oktmo":"91610420101","inn":null,"website":"http://zelenchuksky.kchr.sudrf.ru","objectguid":"b22fd8bc-d18c-4a2e-9039-1506bd0cd8a0","status":"found"},{"code":"09RS0008","name":"Хабезский районный суд Карачаево-Черкесской Республики","court_type":"RS","address":"369400, Респ Карачаево-Черкесская, аул Хабез, ул У.Хабекова, зд 64","oktmo":"91640440101","inn":null,"website":"http://xabezsky.kchr.sudrf.ru","objectguid":"b5efc507-f789-45df-ac8d-74c7bc744a7e","status":"found"},{"code":"09RS0009","name":"Адыге-Хабльский районный суд Карачаево-Черкесской Республики","court_type":"RS","address":"369330, Респ Карачаево-Черкесская, аул Адыге-Хабль, ул Хусина Гашокова, д 3","oktmo":"91603408101","inn":null,"website":"http://adige-hablsky.kchr.sudrf.ru","objectguid":"114e8ae4-870a-4519-bbfd-68b045900930","status":"found"},{"code":"09RS0010","name":"Прикубанский районный суд Карачаево-Черкесской Республики","court_type":"RS","address":"369100, Респ Карачаево-Черкесская, Прикубанский р-н, п Кавказский, пр-кт Ленина, д 6","oktmo":"91625420101","inn":null,"website":"http://prikubansky.kchr.sudrf.ru","objectguid":"556ca79a-df03-4bda-b1cf-d2e40e782953","status":"found"}]